code4/__init__.py
code4-0.0.1.dist-info/LICENSE
code4-0.0.1.dist-info/METADATA
code4-0.0.1.dist-info/WHEEL
code4-0.0.1.dist-info/top_level.txt
code4-0.0.1.dist-info/RECORD
